slycat/__init__.py
slycat/darray.py
slycat/pandas_util.py
slycat/web/__init__.py
slycat/web/client/__init__.py
slycat/web/client/cca_csv.py
slycat/web/client/cca_random.py
slycat/web/client/dac_defaults.py
slycat/web/client/dac_gen.py
slycat/web/client/dac_run_chart.py
slycat/web/client/dac_tdms.py
slycat/web/client/dac_tdms_batches.py
slycat/web/client/dac_tdms_from_file.py
slycat/web/client/dac_tdms_util.py
slycat/web/client/get_model.py
slycat/web/client/get_project.py
slycat/web/client/list_markings.py
slycat/web/client/list_projects.py
slycat/web/client/ps_csv.py
slycat_web_client-4.5.2.dist-info/LICENSE
slycat_web_client-4.5.2.dist-info/METADATA
slycat_web_client-4.5.2.dist-info/WHEEL
slycat_web_client-4.5.2.dist-info/entry_points.txt
slycat_web_client-4.5.2.dist-info/top_level.txt
slycat_web_client-4.5.2.dist-info/RECORD
