Metadata-Version: 2.2
Name: slycat-web-client
Version: 4.5.2
Summary: Slycat web client utilties for interacting with the Slycat data analysis and visualization server.
Home-page: https://github.com/sandialabs/slycat
Author: Shawn Martin
Author-email: smartin@sandia.gov
License: Sandia
Classifier: Programming Language :: Python :: 3
Classifier: Programming Language :: Python :: 3.13
License-File: LICENSE
Requires-Dist: requests
Requires-Dist: requests-kerberos
Requires-Dist: numpy
Requires-Dist: cherrypy
Requires-Dist: scikit-learn
Requires-Dist: npTDMS
Requires-Dist: pandas
Requires-Dist: natsort
Dynamic: author
Dynamic: author-email
Dynamic: classifier
Dynamic: description
Dynamic: description-content-type
Dynamic: home-page
Dynamic: license
Dynamic: requires-dist
Dynamic: summary
